conductor/__init__.py
conductor/client.py
conductor/helper.py
conductor/manager.py
python_conductor-0.2.1.dist-info/LICENSE.txt
python_conductor-0.2.1.dist-info/METADATA
python_conductor-0.2.1.dist-info/WHEEL
python_conductor-0.2.1.dist-info/top_level.txt
python_conductor-0.2.1.dist-info/RECORD
