Metadata-Version: 2.1
Name: python-conductor
Version: 0.2.1
Summary: A simple python wrapper for Netflix Conductor task execution
Home-page: https://github.com/ypk46/python-conductor
Author: Yuyi Pacheco K.
Author-email: yuyik46@gmail.com
License: MIT
Download-URL: https://github.com/ypk46/python-conductor/archive/v0.1.0.tar.gz
Keywords: conductor
Platform: UNKNOWN
Classifier: Development Status :: 3 - Alpha
Classifier: Intended Audience :: Developers
Classifier: Topic :: Software Development :: Libraries
Classifier: License :: OSI Approved :: MIT License
Classifier: Programming Language :: Python :: 3
Classifier: Programming Language :: Python :: 3.5
Classifier: Programming Language :: Python :: 3.6
Classifier: Programming Language :: Python :: 3.7
Requires-Dist: requests
